LICENSE
MANIFEST.in
README.rst
setup.py
helga_productpages/__init__.py
helga_productpages/task.py
helga_productpages/util.py
helga_productpages.egg-info/PKG-INFO
helga_productpages.egg-info/SOURCES.txt
helga_productpages.egg-info/dependency_links.txt
helga_productpages.egg-info/entry_points.txt
helga_productpages.egg-info/requires.txt
helga_productpages.egg-info/top_level.txt
helga_productpages/actions/__init__.py
helga_productpages/actions/release_date.py
helga_productpages/actions/release_schedule.py