Metadata-Version: 1.1
Name: helga-productpages
Version: 1.0.1
Summary: Red Hat Product Pages plugin for Helga
Home-page: https://github.com/ktdreyer/helga-productpages
Author: ken dreyer
Author-email: ktdreyer@ktdreyer.com
License: MIT
Keywords: irc bot productpages
Platform: UNKNOWN
Classifier: Development Status :: 4 - Beta
Classifier: License :: OSI Approved :: MIT License
Classifier: Intended Audience :: Developers
Classifier: Operating System :: POSIX
Classifier: Programming Language :: Python
Classifier: Topic :: Software Development
